{
  "landmark": [
    {
      "y": 0.62888604, 
      "x": 0.35912055, 
      "z": 5.9780364e-06, 
      "visibility": 0.0, 
      "presence": 0.0
    }, 
    {
      "y": 0.615812, 
      "x": 0.33790028, 
      "z": -0.017306637, 
      "visibility": 0.0, 
      "presence": 0.0
    }, 
    {
      "y": 0.5799608, 
      "x": 0.32287028, 
      "z": -0.027552735, 
      "visibility": 0.0, 
      "presence": 0.0
    }, 
    {
      "y": 0.5502002, 
      "x": 0.31403598, 
      "z": -0.03615851, 
      "visibility": 0.0, 
      "presence": 0.0
    }, 
    {
      "y": 0.52938986, 
      "x": 0.30321267, 
      "z": -0.045049556, 
      "visibility": 0.0, 
      "presence": 0.0
    }, 
    {
      "y": 0.53949195, 
      "x": 0.34181914, 
      "z": -0.02567468, 
      "visibility": 0.0, 
      "presence": 0.0
    }, 
    {
      "y": 0.5018374, 
      "x": 0.33884108, 
      "z": -0.04043762, 
      "visibility": 0.0, 
      "presence": 0.0
    }, 
    {
      "y": 0.48344865, 
      "x": 0.3370334, 
      "z": -0.051159177, 
      "visibility": 0.0, 
      "presence": 0.0
    }, 
    {
      "y": 0.468128, 
      "x": 0.33600208, 
      "z": -0.058956675, 
      "visibility": 0.0, 
      "presence": 0.0
    }, 
    {
      "y": 0.5361047, 
      "x": 0.35642076, 
      "z": -0.02467622, 
      "visibility": 0.0, 
      "presence": 0.0
    }, 
    {
      "y": 0.4948555, 
      "x": 0.3570986, 
      "z": -0.037703745, 
      "visibility": 0.0, 
      "presence": 0.0
    }, 
    {
      "y": 0.47116256, 
      "x": 0.35714224, 
      "z": -0.049542625, 
      "visibility": 0.0, 
      "presence": 0.0
    }, 
    {
      "y": 0.44995028, 
      "x": 0.35684958, 
      "z": -0.05966986, 
      "visibility": 0.0, 
      "presence": 0.0
    }, 
    {
      "y": 0.5440511, 
      "x": 0.37018254, 
      "z": -0.025389407, 
      "visibility": 0.0, 
      "presence": 0.0
    }, 
    {
      "y": 0.5045754, 
      "x": 0.37327838, 
      "z": -0.038107883, 
      "visibility": 0.0, 
      "presence": 0.0
    }, 
    {
      "y": 0.47989833, 
      "x": 0.37401947, 
      "z": -0.05058863, 
      "visibility": 0.0, 
      "presence": 0.0
    }, 
    {
      "y": 0.45778793, 
      "x": 0.37379882, 
      "z": -0.060478136, 
      "visibility": 0.0, 
      "presence": 0.0
    }, 
    {
      "y": 0.5605517, 
      "x": 0.38274312, 
      "z": -0.026958415, 
      "visibility": 0.0, 
      "presence": 0.0
    }, 
    {
      "y": 0.5330063, 
      "x": 0.38855958, 
      "z": -0.039700665, 
      "visibility": 0.0, 
      "presence": 0.0
    }, 
    {
      "y": 0.5120913, 
      "x": 0.39185137, 
      "z": -0.049732808, 
      "visibility": 0.0, 
      "presence": 0.0
    }, 
    {
      "y": 0.49160436, 
      "x": 0.39442155, 
      "z": -0.058528762, 
      "visibility": 0.0, 
      "presence": 0.0
    }
  ]
}