{
  "landmark": [
    {
      "y": 0.5165201, 
      "x": 0.065198176, 
      "z": 1.5289905e-05, 
      "visibility": 0.0, 
      "presence": 0.0
    }, 
    {
      "y": 0.5089338, 
      "x": 0.098427944, 
      "z": -0.021864183, 
      "visibility": 0.0, 
      "presence": 0.0
    }, 
    {
      "y": 0.47452843, 
      "x": 0.122812964, 
      "z": -0.04223196, 
      "visibility": 0.0, 
      "presence": 0.0
    }, 
    {
      "y": 0.44353157, 
      "x": 0.14089169, 
      "z": -0.062073223, 
      "visibility": 0.0, 
      "presence": 0.0
    }, 
    {
      "y": 0.42168877, 
      "x": 0.16310453, 
      "z": -0.085239835, 
      "visibility": 0.0, 
      "presence": 0.0
    }, 
    {
      "y": 0.42881382, 
      "x": 0.10065543, 
      "z": -0.06323709, 
      "visibility": 0.0, 
      "presence": 0.0
    }, 
    {
      "y": 0.3887924, 
      "x": 0.11113077, 
      "z": -0.091668844, 
      "visibility": 0.0, 
      "presence": 0.0
    }, 
    {
      "y": 0.37012306, 
      "x": 0.121996984, 
      "z": -0.11078962, 
      "visibility": 0.0, 
      "presence": 0.0
    }, 
    {
      "y": 0.3556537, 
      "x": 0.13086008, 
      "z": -0.124811515, 
      "visibility": 0.0, 
      "presence": 0.0
    }, 
    {
      "y": 0.43137345, 
      "x": 0.08402598, 
      "z": -0.06828055, 
      "visibility": 0.0, 
      "presence": 0.0
    }, 
    {
      "y": 0.38787243, 
      "x": 0.086646065, 
      "z": -0.10375096, 
      "visibility": 0.0, 
      "presence": 0.0
    }, 
    {
      "y": 0.36838073, 
      "x": 0.0949838, 
      "z": -0.1260308, 
      "visibility": 0.0, 
      "presence": 0.0
    }, 
    {
      "y": 0.35174912, 
      "x": 0.102264486, 
      "z": -0.14376602, 
      "visibility": 0.0, 
      "presence": 0.0
    }, 
    {
      "y": 0.44639164, 
      "x": 0.067067616, 
      "z": -0.07404449, 
      "visibility": 0.0, 
      "presence": 0.0
    }, 
    {
      "y": 0.4091038, 
      "x": 0.06381117, 
      "z": -0.10807391, 
      "visibility": 0.0, 
      "presence": 0.0
    }, 
    {
      "y": 0.39731604, 
      "x": 0.07073254, 
      "z": -0.1329032, 
      "visibility": 0.0, 
      "presence": 0.0
    }, 
    {
      "y": 0.38994104, 
      "x": 0.077507675, 
      "z": -0.14853235, 
      "visibility": 0.0, 
      "presence": 0.0
    }, 
    {
      "y": 0.46699274, 
      "x": 0.050730474, 
      "z": -0.08052892, 
      "visibility": 0.0, 
      "presence": 0.0
    }, 
    {
      "y": 0.4444652, 
      "x": 0.039318435, 
      "z": -0.10990286, 
      "visibility": 0.0, 
      "presence": 0.0
    }, 
    {
      "y": 0.4331347, 
      "x": 0.038708694, 
      "z": -0.13101883, 
      "visibility": 0.0, 
      "presence": 0.0
    }, 
    {
      "y": 0.42501402, 
      "x": 0.039009493, 
      "z": -0.14819981, 
      "visibility": 0.0, 
      "presence": 0.0
    }
  ]
}