{
  "landmark": [
    {
      "y": 0.70022786, 
      "x": 0.083288625, 
      "z": 7.533876e-06, 
      "visibility": 0.0, 
      "presence": 0.0
    }, 
    {
      "y": 0.69855154, 
      "x": 0.054026473, 
      "z": -0.019959105, 
      "visibility": 0.0, 
      "presence": 0.0
    }, 
    {
      "y": 0.6756115, 
      "x": 0.032277394, 
      "z": -0.04025279, 
      "visibility": 0.0, 
      "presence": 0.0
    }, 
    {
      "y": 0.6534036, 
      "x": 0.019866582, 
      "z": -0.057342213, 
      "visibility": 0.0, 
      "presence": 0.0
    }, 
    {
      "y": 0.6367635, 
      "x": 0.017820818, 
      "z": -0.07906431, 
      "visibility": 0.0, 
      "presence": 0.0
    }, 
    {
      "y": 0.6730012, 
      "x": 0.04249067, 
      "z": -0.080093786, 
      "visibility": 0.0, 
      "presence": 0.0
    }, 
    {
      "y": 0.6455878, 
      "x": 0.024966666, 
      "z": -0.11303725, 
      "visibility": 0.0, 
      "presence": 0.0
    }, 
    {
      "y": 0.62788486, 
      "x": 0.019221587, 
      "z": -0.13033257, 
      "visibility": 0.0, 
      "presence": 0.0
    }, 
    {
      "y": 0.6185867, 
      "x": 0.01703782, 
      "z": -0.14011265, 
      "visibility": 0.0, 
      "presence": 0.0
    }, 
    {
      "y": 0.6578181, 
      "x": 0.060286894, 
      "z": -0.08132917, 
      "visibility": 0.0, 
      "presence": 0.0
    }, 
    {
      "y": 0.62783515, 
      "x": 0.0477775, 
      "z": -0.12261144, 
      "visibility": 0.0, 
      "presence": 0.0
    }, 
    {
      "y": 0.60321224, 
      "x": 0.04294388, 
      "z": -0.14320111, 
      "visibility": 0.0, 
      "presence": 0.0
    }, 
    {
      "y": 0.5895873, 
      "x": 0.03902286, 
      "z": -0.1591581, 
      "visibility": 0.0, 
      "presence": 0.0
    }, 
    {
      "y": 0.64990956, 
      "x": 0.07874377, 
      "z": -0.08081443, 
      "visibility": 0.0, 
      "presence": 0.0
    }, 
    {
      "y": 0.619041, 
      "x": 0.07371426, 
      "z": -0.119522996, 
      "visibility": 0.0, 
      "presence": 0.0
    }, 
    {
      "y": 0.5898972, 
      "x": 0.068373926, 
      "z": -0.1461866, 
      "visibility": 0.0, 
      "presence": 0.0
    }, 
    {
      "y": 0.57196164, 
      "x": 0.0638244, 
      "z": -0.165335, 
      "visibility": 0.0, 
      "presence": 0.0
    }, 
    {
      "y": 0.64853907, 
      "x": 0.096567795, 
      "z": -0.078549564, 
      "visibility": 0.0, 
      "presence": 0.0
    }, 
    {
      "y": 0.62081933, 
      "x": 0.101584174, 
      "z": -0.10871342, 
      "visibility": 0.0, 
      "presence": 0.0
    }, 
    {
      "y": 0.60095394, 
      "x": 0.10153547, 
      "z": -0.13043551, 
      "visibility": 0.0, 
      "presence": 0.0
    }, 
    {
      "y": 0.5884129, 
      "x": 0.09922296, 
      "z": -0.14824557, 
      "visibility": 0.0, 
      "presence": 0.0
    }
  ]
}