{
  "landmark": [
    {
      "y": 0.65004015, 
      "x": 0.49379602, 
      "z": 1.6931988e-05, 
      "visibility": 0.0, 
      "presence": 0.0
    }, 
    {
      "y": 0.634971, 
      "x": 0.5152268, 
      "z": -0.032072894, 
      "visibility": 0.0, 
      "presence": 0.0
    }, 
    {
      "y": 0.6061844, 
      "x": 0.5256322, 
      "z": -0.063104264, 
      "visibility": 0.0, 
      "presence": 0.0
    }, 
    {
      "y": 0.59508425, 
      "x": 0.53203315, 
      "z": -0.088713564, 
      "visibility": 0.0, 
      "presence": 0.0
    }, 
    {
      "y": 0.58596873, 
      "x": 0.5422297, 
      "z": -0.11622212, 
      "visibility": 0.0, 
      "presence": 0.0
    }, 
    {
      "y": 0.53730124, 
      "x": 0.4915277, 
      "z": -0.07088508, 
      "visibility": 0.0, 
      "presence": 0.0
    }, 
    {
      "y": 0.4863764, 
      "x": 0.48102647, 
      "z": -0.097903505, 
      "visibility": 0.0, 
      "presence": 0.0
    }, 
    {
      "y": 0.4608007, 
      "x": 0.4740098, 
      "z": -0.11738618, 
      "visibility": 0.0, 
      "presence": 0.0
    }, 
    {
      "y": 0.4436161, 
      "x": 0.4673669, 
      "z": -0.13012956, 
      "visibility": 0.0, 
      "presence": 0.0
    }, 
    {
      "y": 0.54665065, 
      "x": 0.4699002, 
      "z": -0.068128094, 
      "visibility": 0.0, 
      "presence": 0.0
    }, 
    {
      "y": 0.49215564, 
      "x": 0.45275173, 
      "z": -0.09251207, 
      "visibility": 0.0, 
      "presence": 0.0
    }, 
    {
      "y": 0.46254668, 
      "x": 0.44053912, 
      "z": -0.108196236, 
      "visibility": 0.0, 
      "presence": 0.0
    }, 
    {
      "y": 0.4366623, 
      "x": 0.42852297, 
      "z": -0.121123426, 
      "visibility": 0.0, 
      "presence": 0.0
    }, 
    {
      "y": 0.5726196, 
      "x": 0.45477742, 
      "z": -0.06549364, 
      "visibility": 0.0, 
      "presence": 0.0
    }, 
    {
      "y": 0.52968097, 
      "x": 0.432307, 
      "z": -0.09073535, 
      "visibility": 0.0, 
      "presence": 0.0
    }, 
    {
      "y": 0.50331575, 
      "x": 0.4171312, 
      "z": -0.10501039, 
      "visibility": 0.0, 
      "presence": 0.0
    }, 
    {
      "y": 0.47929832, 
      "x": 0.4044378, 
      "z": -0.11438413, 
      "visibility": 0.0, 
      "presence": 0.0
    }, 
    {
      "y": 0.6083138, 
      "x": 0.44348362, 
      "z": -0.06328806, 
      "visibility": 0.0, 
      "presence": 0.0
    }, 
    {
      "y": 0.5824451, 
      "x": 0.41682392, 
      "z": -0.083567195, 
      "visibility": 0.0, 
      "presence": 0.0
    }, 
    {
      "y": 0.5707627, 
      "x": 0.39982656, 
      "z": -0.093982466, 
      "visibility": 0.0, 
      "presence": 0.0
    }, 
    {
      "y": 0.55561996, 
      "x": 0.38505545, 
      "z": -0.10084429, 
      "visibility": 0.0, 
      "presence": 0.0
    }
  ]
}