{
  "landmark": [
    {
      "y": 0.71028256, 
      "x": 0.5471638, 
      "z": 1.1510354e-05, 
      "visibility": 0.0, 
      "presence": 0.0
    }, 
    {
      "y": 0.67022216, 
      "x": 0.5213937, 
      "z": 0.01097131, 
      "visibility": 0.0, 
      "presence": 0.0
    }, 
    {
      "y": 0.6268731, 
      "x": 0.508423, 
      "z": 0.0034931074, 
      "visibility": 0.0, 
      "presence": 0.0
    }, 
    {
      "y": 0.5926013, 
      "x": 0.50062644, 
      "z": -0.0027410702, 
      "visibility": 0.0, 
      "presence": 0.0
    }, 
    {
      "y": 0.56320065, 
      "x": 0.496608, 
      "z": -0.010394982, 
      "visibility": 0.0, 
      "presence": 0.0
    }, 
    {
      "y": 0.63013047, 
      "x": 0.50242406, 
      "z": -0.068990625, 
      "visibility": 0.0, 
      "presence": 0.0
    }, 
    {
      "y": 0.5756304, 
      "x": 0.48524123, 
      "z": -0.09575472, 
      "visibility": 0.0, 
      "presence": 0.0
    }, 
    {
      "y": 0.5310503, 
      "x": 0.4786145, 
      "z": -0.10936167, 
      "visibility": 0.0, 
      "presence": 0.0
    }, 
    {
      "y": 0.49527186, 
      "x": 0.4748953, 
      "z": -0.11841423, 
      "visibility": 0.0, 
      "presence": 0.0
    }, 
    {
      "y": 0.64093035, 
      "x": 0.51832217, 
      "z": -0.08287872, 
      "visibility": 0.0, 
      "presence": 0.0
    }, 
    {
      "y": 0.5807045, 
      "x": 0.50813615, 
      "z": -0.122012764, 
      "visibility": 0.0, 
      "presence": 0.0
    }, 
    {
      "y": 0.5301002, 
      "x": 0.5058771, 
      "z": -0.13685672, 
      "visibility": 0.0, 
      "presence": 0.0
    }, 
    {
      "y": 0.49145296, 
      "x": 0.5053242, 
      "z": -0.14888932, 
      "visibility": 0.0, 
      "presence": 0.0
    }, 
    {
      "y": 0.65084064, 
      "x": 0.539039, 
      "z": -0.09080674, 
      "visibility": 0.0, 
      "presence": 0.0
    }, 
    {
      "y": 0.5992626, 
      "x": 0.5370002, 
      "z": -0.12909737, 
      "visibility": 0.0, 
      "presence": 0.0
    }, 
    {
      "y": 0.5522147, 
      "x": 0.5363009, 
      "z": -0.14945158, 
      "visibility": 0.0, 
      "presence": 0.0
    }, 
    {
      "y": 0.51685154, 
      "x": 0.53692245, 
      "z": -0.16294608, 
      "visibility": 0.0, 
      "presence": 0.0
    }, 
    {
      "y": 0.65779424, 
      "x": 0.56040615, 
      "z": -0.09316827, 
      "visibility": 0.0, 
      "presence": 0.0
    }, 
    {
      "y": 0.6155137, 
      "x": 0.5683328, 
      "z": -0.12122559, 
      "visibility": 0.0, 
      "presence": 0.0
    }, 
    {
      "y": 0.58466417, 
      "x": 0.5727283, 
      "z": -0.13359554, 
      "visibility": 0.0, 
      "presence": 0.0
    }, 
    {
      "y": 0.5597134, 
      "x": 0.57622546, 
      "z": -0.14394133, 
      "visibility": 0.0, 
      "presence": 0.0
    }
  ]
}