{
  "landmark": [
    {
      "y": 0.551018, 
      "x": 0.09936321, 
      "z": 2.054236e-05, 
      "visibility": 0.0, 
      "presence": 0.0
    }, 
    {
      "y": 0.5376203, 
      "x": 0.13285626, 
      "z": -0.032931246, 
      "visibility": 0.0, 
      "presence": 0.0
    }, 
    {
      "y": 0.5034959, 
      "x": 0.15744933, 
      "z": -0.059769485, 
      "visibility": 0.0, 
      "presence": 0.0
    }, 
    {
      "y": 0.48382944, 
      "x": 0.17819874, 
      "z": -0.08261825, 
      "visibility": 0.0, 
      "presence": 0.0
    }, 
    {
      "y": 0.47902903, 
      "x": 0.20188996, 
      "z": -0.109311424, 
      "visibility": 0.0, 
      "presence": 0.0
    }, 
    {
      "y": 0.46572733, 
      "x": 0.13385342, 
      "z": -0.08145768, 
      "visibility": 0.0, 
      "presence": 0.0
    }, 
    {
      "y": 0.42391607, 
      "x": 0.1454931, 
      "z": -0.12178758, 
      "visibility": 0.0, 
      "presence": 0.0
    }, 
    {
      "y": 0.40238386, 
      "x": 0.15766253, 
      "z": -0.14550678, 
      "visibility": 0.0, 
      "presence": 0.0
    }, 
    {
      "y": 0.38473755, 
      "x": 0.1689608, 
      "z": -0.15653221, 
      "visibility": 0.0, 
      "presence": 0.0
    }, 
    {
      "y": 0.46014485, 
      "x": 0.11232045, 
      "z": -0.08261825, 
      "visibility": 0.0, 
      "presence": 0.0
    }, 
    {
      "y": 0.40743724, 
      "x": 0.11361806, 
      "z": -0.11932136, 
      "visibility": 0.0, 
      "presence": 0.0
    }, 
    {
      "y": 0.37480593, 
      "x": 0.12092049, 
      "z": -0.14449127, 
      "visibility": 0.0, 
      "presence": 0.0
    }, 
    {
      "y": 0.3411344, 
      "x": 0.12861787, 
      "z": -0.1637858, 
      "visibility": 0.0, 
      "presence": 0.0
    }, 
    {
      "y": 0.47285235, 
      "x": 0.09138187, 
      "z": -0.085229546, 
      "visibility": 0.0, 
      "presence": 0.0
    }, 
    {
      "y": 0.42383856, 
      "x": 0.08452074, 
      "z": -0.11917629, 
      "visibility": 0.0, 
      "presence": 0.0
    }, 
    {
      "y": 0.39059538, 
      "x": 0.08534529, 
      "z": -0.1412997, 
      "visibility": 0.0, 
      "presence": 0.0
    }, 
    {
      "y": 0.35503566, 
      "x": 0.08778604, 
      "z": -0.15841815, 
      "visibility": 0.0, 
      "presence": 0.0
    }, 
    {
      "y": 0.49854437, 
      "x": 0.07246512, 
      "z": -0.088421114, 
      "visibility": 0.0, 
      "presence": 0.0
    }, 
    {
      "y": 0.4716356, 
      "x": 0.056094505, 
      "z": -0.117000215, 
      "visibility": 0.0, 
      "presence": 0.0
    }, 
    {
      "y": 0.45168862, 
      "x": 0.048014864, 
      "z": -0.13614966, 
      "visibility": 0.0, 
      "presence": 0.0
    }, 
    {
      "y": 0.42747322, 
      "x": 0.04249969, 
      "z": -0.15290543, 
      "visibility": 0.0, 
      "presence": 0.0
    }
  ]
}