{
  "landmark": [
    {
      "y": 0.41980594, 
      "x": 0.15212452, 
      "z": 2.5111338e-05, 
      "visibility": 0.0, 
      "presence": 0.0
    }, 
    {
      "y": 0.4263522, 
      "x": 0.19023348, 
      "z": -0.044506565, 
      "visibility": 0.0, 
      "presence": 0.0
    }, 
    {
      "y": 0.39359754, 
      "x": 0.21844478, 
      "z": -0.07589456, 
      "visibility": 0.0, 
      "presence": 0.0
    }, 
    {
      "y": 0.35757375, 
      "x": 0.23848638, 
      "z": -0.10205121, 
      "visibility": 0.0, 
      "presence": 0.0
    }, 
    {
      "y": 0.33116025, 
      "x": 0.2620749, 
      "z": -0.12933463, 
      "visibility": 0.0, 
      "presence": 0.0
    }, 
    {
      "y": 0.28689834, 
      "x": 0.19422412, 
      "z": -0.07726275, 
      "visibility": 0.0, 
      "presence": 0.0
    }, 
    {
      "y": 0.21652274, 
      "x": 0.20724064, 
      "z": -0.10768496, 
      "visibility": 0.0, 
      "presence": 0.0
    }, 
    {
      "y": 0.16919291, 
      "x": 0.21539482, 
      "z": -0.1316686, 
      "visibility": 0.0, 
      "presence": 0.0
    }, 
    {
      "y": 0.12607375, 
      "x": 0.21968211, 
      "z": -0.15042092, 
      "visibility": 0.0, 
      "presence": 0.0
    }, 
    {
      "y": 0.27047563, 
      "x": 0.16538398, 
      "z": -0.07271551, 
      "visibility": 0.0, 
      "presence": 0.0
    }, 
    {
      "y": 0.18749659, 
      "x": 0.16986704, 
      "z": -0.09891242, 
      "visibility": 0.0, 
      "presence": 0.0
    }, 
    {
      "y": 0.13355055, 
      "x": 0.17283781, 
      "z": -0.11774521, 
      "visibility": 0.0, 
      "presence": 0.0
    }, 
    {
      "y": 0.08471428, 
      "x": 0.17184407, 
      "z": -0.13376114, 
      "visibility": 0.0, 
      "presence": 0.0
    }, 
    {
      "y": 0.27468526, 
      "x": 0.13823855, 
      "z": -0.07038154, 
      "visibility": 0.0, 
      "presence": 0.0
    }, 
    {
      "y": 0.19600067, 
      "x": 0.12907514, 
      "z": -0.0958541, 
      "visibility": 0.0, 
      "presence": 0.0
    }, 
    {
      "y": 0.1455318, 
      "x": 0.12196356, 
      "z": -0.11500882, 
      "visibility": 0.0, 
      "presence": 0.0
    }, 
    {
      "y": 0.10127491, 
      "x": 0.114439934, 
      "z": -0.129898, 
      "visibility": 0.0, 
      "presence": 0.0
    }, 
    {
      "y": 0.2972499, 
      "x": 0.11362521, 
      "z": -0.07046202, 
      "visibility": 0.0, 
      "presence": 0.0
    }, 
    {
      "y": 0.23946288, 
      "x": 0.09809495, 
      "z": -0.09537121, 
      "visibility": 0.0, 
      "presence": 0.0
    }, 
    {
      "y": 0.20341733, 
      "x": 0.08443407, 
      "z": -0.110421345, 
      "visibility": 0.0, 
      "presence": 0.0
    }, 
    {
      "y": 0.16607487, 
      "x": 0.07175005, 
      "z": -0.12241317, 
      "visibility": 0.0, 
      "presence": 0.0
    }
  ]
}