{
  "landmark": [
    {
      "y": 0.66417325, 
      "x": 0.4585052, 
      "z": 2.1579615e-05, 
      "visibility": 0.0, 
      "presence": 0.0
    }, 
    {
      "y": 0.6135752, 
      "x": 0.4750946, 
      "z": -0.051354494, 
      "visibility": 0.0, 
      "presence": 0.0
    }, 
    {
      "y": 0.57799315, 
      "x": 0.47520965, 
      "z": -0.09171828, 
      "visibility": 0.0, 
      "presence": 0.0
    }, 
    {
      "y": 0.5643041, 
      "x": 0.47117984, 
      "z": -0.122678034, 
      "visibility": 0.0, 
      "presence": 0.0
    }, 
    {
      "y": 0.5552782, 
      "x": 0.46850884, 
      "z": -0.15348299, 
      "visibility": 0.0, 
      "presence": 0.0
    }, 
    {
      "y": 0.5442342, 
      "x": 0.41393197, 
      "z": -0.09326626, 
      "visibility": 0.0, 
      "presence": 0.0
    }, 
    {
      "y": 0.5086633, 
      "x": 0.38321108, 
      "z": -0.12933438, 
      "visibility": 0.0, 
      "presence": 0.0
    }, 
    {
      "y": 0.494285, 
      "x": 0.36345118, 
      "z": -0.15843655, 
      "visibility": 0.0, 
      "presence": 0.0
    }, 
    {
      "y": 0.48997498, 
      "x": 0.3453885, 
      "z": -0.17972139, 
      "visibility": 0.0, 
      "presence": 0.0
    }, 
    {
      "y": 0.5786333, 
      "x": 0.39283282, 
      "z": -0.08544893, 
      "visibility": 0.0, 
      "presence": 0.0
    }, 
    {
      "y": 0.54504687, 
      "x": 0.35542545, 
      "z": -0.12476782, 
      "visibility": 0.0, 
      "presence": 0.0
    }, 
    {
      "y": 0.5311841, 
      "x": 0.33065885, 
      "z": -0.15487619, 
      "visibility": 0.0, 
      "presence": 0.0
    }, 
    {
      "y": 0.5224653, 
      "x": 0.30659896, 
      "z": -0.17894739, 
      "visibility": 0.0, 
      "presence": 0.0
    }, 
    {
      "y": 0.6192784, 
      "x": 0.38469195, 
      "z": -0.07805729, 
      "visibility": 0.0, 
      "presence": 0.0
    }, 
    {
      "y": 0.5996376, 
      "x": 0.3461767, 
      "z": -0.11145512, 
      "visibility": 0.0, 
      "presence": 0.0
    }, 
    {
      "y": 0.59127814, 
      "x": 0.3212188, 
      "z": -0.13583593, 
      "visibility": 0.0, 
      "presence": 0.0
    }, 
    {
      "y": 0.5822321, 
      "x": 0.2970854, 
      "z": -0.1517028, 
      "visibility": 0.0, 
      "presence": 0.0
    }, 
    {
      "y": 0.66537076, 
      "x": 0.38520724, 
      "z": -0.07240713, 
      "visibility": 0.0, 
      "presence": 0.0
    }, 
    {
      "y": 0.66482663, 
      "x": 0.35056102, 
      "z": -0.10015481, 
      "visibility": 0.0, 
      "presence": 0.0
    }, 
    {
      "y": 0.66592216, 
      "x": 0.32706895, 
      "z": -0.11950466, 
      "visibility": 0.0, 
      "presence": 0.0
    }, 
    {
      "y": 0.66175365, 
      "x": 0.3036918, 
      "z": -0.13304955, 
      "visibility": 0.0, 
      "presence": 0.0
    }
  ]
}