{
  "locationData": {
    "relativeBoundingBox": {
      "xmin": 0.48514107, 
      "width": 0.07040903, 
      "ymin": 0.46713537, 
      "height": 0.1251716
    }, 
    "relativeKeypoints": [
      {
        "y": 0.58739936, 
        "x": 0.5362801
      }, 
      {
        "y": 0.4732053, 
        "x": 0.5228029
      }, 
      {
        "y": 0.49174166, 
        "x": 0.5051593
      }, 
      {
        "y": 0.51598835, 
        "x": 0.4919565
      }, 
      {
        "y": 0.5414506, 
        "x": 0.48264354
      }, 
      {
        "y": 0.55625606, 
        "x": 0.5523613
      }, 
      {
        "y": 0.50474995, 
        "x": 0.5470482
      }
    ], 
    "format": "RELATIVE_BOUNDING_BOX"
  }, 
  "score": [
    0.99983263
  ], 
  "label": [
    "Palm"
  ]
}