{
  "landmark": [
    {
      "y": 0.507518, 
      "x": 0.669465, 
      "z": 1.0417239e-05, 
      "visibility": 0.0, 
      "presence": 0.0
    }, 
    {
      "y": 0.55263686, 
      "x": 0.63960063, 
      "z": -0.02069093, 
      "visibility": 0.0, 
      "presence": 0.0
    }, 
    {
      "y": 0.559245, 
      "x": 0.60259384, 
      "z": -0.033701867, 
      "visibility": 0.0, 
      "presence": 0.0
    }, 
    {
      "y": 0.56313014, 
      "x": 0.5704349, 
      "z": -0.046680626, 
      "visibility": 0.0, 
      "presence": 0.0
    }, 
    {
      "y": 0.58037406, 
      "x": 0.5466935, 
      "z": -0.06375681, 
      "visibility": 0.0, 
      "presence": 0.0
    }, 
    {
      "y": 0.45679516, 
      "x": 0.57508594, 
      "z": -0.03685538, 
      "visibility": 0.0, 
      "presence": 0.0
    }, 
    {
      "y": 0.4257775, 
      "x": 0.53637916, 
      "z": -0.059251785, 
      "visibility": 0.0, 
      "presence": 0.0
    }, 
    {
      "y": 0.40516478, 
      "x": 0.51434565, 
      "z": -0.07362495, 
      "visibility": 0.0, 
      "presence": 0.0
    }, 
    {
      "y": 0.3872977, 
      "x": 0.4964172, 
      "z": -0.08443701, 
      "visibility": 0.0, 
      "presence": 0.0
    }, 
    {
      "y": 0.41484153, 
      "x": 0.5866818, 
      "z": -0.039472587, 
      "visibility": 0.0, 
      "presence": 0.0
    }, 
    {
      "y": 0.36962023, 
      "x": 0.5481075, 
      "z": -0.06083927, 
      "visibility": 0.0, 
      "presence": 0.0
    }, 
    {
      "y": 0.33988318, 
      "x": 0.52250147, 
      "z": -0.07714316, 
      "visibility": 0.0, 
      "presence": 0.0
    }, 
    {
      "y": 0.3136346, 
      "x": 0.5001964, 
      "z": -0.09164505, 
      "visibility": 0.0, 
      "presence": 0.0
    }, 
    {
      "y": 0.39057216, 
      "x": 0.60758436, 
      "z": -0.044320848, 
      "visibility": 0.0, 
      "presence": 0.0
    }, 
    {
      "y": 0.3350029, 
      "x": 0.5788525, 
      "z": -0.06894831, 
      "visibility": 0.0, 
      "presence": 0.0
    }, 
    {
      "y": 0.29948226, 
      "x": 0.55856526, 
      "z": -0.08709712, 
      "visibility": 0.0, 
      "presence": 0.0
    }, 
    {
      "y": 0.270615, 
      "x": 0.539061, 
      "z": -0.10031185, 
      "visibility": 0.0, 
      "presence": 0.0
    }, 
    {
      "y": 0.38033342, 
      "x": 0.6350437, 
      "z": -0.04976978, 
      "visibility": 0.0, 
      "presence": 0.0
    }, 
    {
      "y": 0.3200606, 
      "x": 0.6268207, 
      "z": -0.07439724, 
      "visibility": 0.0, 
      "presence": 0.0
    }, 
    {
      "y": 0.27884084, 
      "x": 0.6189509, 
      "z": -0.09052952, 
      "visibility": 0.0, 
      "presence": 0.0
    }, 
    {
      "y": 0.24080516, 
      "x": 0.6069013, 
      "z": -0.103229396, 
      "visibility": 0.0, 
      "presence": 0.0
    }
  ]
}