{
  "locationData": {
    "relativeBoundingBox": {
      "xmin": 0.81213814, 
      "width": 0.076078534, 
      "ymin": 0.59760207, 
      "height": 0.09509809
    }, 
    "relativeKeypoints": [
      {
        "y": 0.6098519, 
        "x": 0.86547625
      }, 
      {
        "y": 0.6783907, 
        "x": 0.8302647
      }, 
      {
        "y": 0.68207365, 
        "x": 0.85326254
      }, 
      {
        "y": 0.68038374, 
        "x": 0.8729342
      }, 
      {
        "y": 0.6750546, 
        "x": 0.88936675
      }, 
      {
        "y": 0.61249983, 
        "x": 0.83435076
      }, 
      {
        "y": 0.64266235, 
        "x": 0.81252956
      }
    ], 
    "format": "RELATIVE_BOUNDING_BOX"
  }, 
  "score": [
    0.9998785
  ], 
  "label": [
    "Palm"
  ]
}