{
  "landmark": [
    {
      "y": 0.62793404, 
      "x": 0.8685661, 
      "z": 5.654808e-06, 
      "visibility": 0.0, 
      "presence": 0.0
    }, 
    {
      "y": 0.63709545, 
      "x": 0.89655155, 
      "z": -0.015451319, 
      "visibility": 0.0, 
      "presence": 0.0
    }, 
    {
      "y": 0.6635023, 
      "x": 0.9170297, 
      "z": -0.02423386, 
      "visibility": 0.0, 
      "presence": 0.0
    }, 
    {
      "y": 0.6890773, 
      "x": 0.9315421, 
      "z": -0.032361433, 
      "visibility": 0.0, 
      "presence": 0.0
    }, 
    {
      "y": 0.70633245, 
      "x": 0.9466445, 
      "z": -0.041233286, 
      "visibility": 0.0, 
      "presence": 0.0
    }, 
    {
      "y": 0.7069121, 
      "x": 0.89127177, 
      "z": -0.016389115, 
      "visibility": 0.0, 
      "presence": 0.0
    }, 
    {
      "y": 0.7446339, 
      "x": 0.8964004, 
      "z": -0.02412966, 
      "visibility": 0.0, 
      "presence": 0.0
    }, 
    {
      "y": 0.7689139, 
      "x": 0.8986307, 
      "z": -0.03140875, 
      "visibility": 0.0, 
      "presence": 0.0
    }, 
    {
      "y": 0.7900461, 
      "x": 0.90056276, 
      "z": -0.039179064, 
      "visibility": 0.0, 
      "presence": 0.0
    }, 
    {
      "y": 0.71062803, 
      "x": 0.87315255, 
      "z": -0.017326912, 
      "visibility": 0.0, 
      "presence": 0.0
    }, 
    {
      "y": 0.75273615, 
      "x": 0.87533313, 
      "z": -0.025826626, 
      "visibility": 0.0, 
      "presence": 0.0
    }, 
    {
      "y": 0.77946573, 
      "x": 0.8774004, 
      "z": -0.035606507, 
      "visibility": 0.0, 
      "presence": 0.0
    }, 
    {
      "y": 0.80288875, 
      "x": 0.8798729, 
      "z": -0.046086013, 
      "visibility": 0.0, 
      "presence": 0.0
    }, 
    {
      "y": 0.7055476, 
      "x": 0.8558093, 
      "z": -0.019574648, 
      "visibility": 0.0, 
      "presence": 0.0
    }, 
    {
      "y": 0.74536544, 
      "x": 0.85291815, 
      "z": -0.028848415, 
      "visibility": 0.0, 
      "presence": 0.0
    }, 
    {
      "y": 0.7714318, 
      "x": 0.85292226, 
      "z": -0.038345467, 
      "visibility": 0.0, 
      "presence": 0.0
    }, 
    {
      "y": 0.7953632, 
      "x": 0.85441035, 
      "z": -0.04647304, 
      "visibility": 0.0, 
      "presence": 0.0
    }, 
    {
      "y": 0.6934378, 
      "x": 0.8396923, 
      "z": -0.023087664, 
      "visibility": 0.0, 
      "presence": 0.0
    }, 
    {
      "y": 0.7205471, 
      "x": 0.82857186, 
      "z": -0.033075944, 
      "visibility": 0.0, 
      "presence": 0.0
    }, 
    {
      "y": 0.73849475, 
      "x": 0.821624, 
      "z": -0.03885158, 
      "visibility": 0.0, 
      "presence": 0.0
    }, 
    {
      "y": 0.75702304, 
      "x": 0.8161403, 
      "z": -0.04418065, 
      "visibility": 0.0, 
      "presence": 0.0
    }
  ]
}