{
  "landmark": [
    {
      "y": 0.6560724, 
      "x": 0.8709824, 
      "z": 1.8527058e-05, 
      "visibility": 0.0, 
      "presence": 0.0
    }, 
    {
      "y": 0.6658945, 
      "x": 0.83865213, 
      "z": -0.014345048, 
      "visibility": 0.0, 
      "presence": 0.0
    }, 
    {
      "y": 0.6945929, 
      "x": 0.82041055, 
      "z": -0.027759954, 
      "visibility": 0.0, 
      "presence": 0.0
    }, 
    {
      "y": 0.7262502, 
      "x": 0.80946493, 
      "z": -0.03633972, 
      "visibility": 0.0, 
      "presence": 0.0
    }, 
    {
      "y": 0.75030124, 
      "x": 0.7974672, 
      "z": -0.046731662, 
      "visibility": 0.0, 
      "presence": 0.0
    }, 
    {
      "y": 0.7310893, 
      "x": 0.8509556, 
      "z": -0.052793626, 
      "visibility": 0.0, 
      "presence": 0.0
    }, 
    {
      "y": 0.78012407, 
      "x": 0.8445222, 
      "z": -0.06690614, 
      "visibility": 0.0, 
      "presence": 0.0
    }, 
    {
      "y": 0.81032735, 
      "x": 0.84194136, 
      "z": -0.07691319, 
      "visibility": 0.0, 
      "presence": 0.0
    }, 
    {
      "y": 0.8327377, 
      "x": 0.8420358, 
      "z": -0.0839053, 
      "visibility": 0.0, 
      "presence": 0.0
    }, 
    {
      "y": 0.7357462, 
      "x": 0.8731236, 
      "z": -0.045384556, 
      "visibility": 0.0, 
      "presence": 0.0
    }, 
    {
      "y": 0.7903636, 
      "x": 0.8738314, 
      "z": -0.05981781, 
      "visibility": 0.0, 
      "presence": 0.0
    }, 
    {
      "y": 0.8242163, 
      "x": 0.8749857, 
      "z": -0.06514207, 
      "visibility": 0.0, 
      "presence": 0.0
    }, 
    {
      "y": 0.8500823, 
      "x": 0.878418, 
      "z": -0.070562564, 
      "visibility": 0.0, 
      "presence": 0.0
    }, 
    {
      "y": 0.73379356, 
      "x": 0.89080936, 
      "z": -0.035505798, 
      "visibility": 0.0, 
      "presence": 0.0
    }, 
    {
      "y": 0.78355765, 
      "x": 0.89555985, 
      "z": -0.04400538, 
      "visibility": 0.0, 
      "presence": 0.0
    }, 
    {
      "y": 0.81444097, 
      "x": 0.9003509, 
      "z": -0.048816465, 
      "visibility": 0.0, 
      "presence": 0.0
    }, 
    {
      "y": 0.83797264, 
      "x": 0.90590054, 
      "z": -0.054942578, 
      "visibility": 0.0, 
      "presence": 0.0
    }, 
    {
      "y": 0.7262277, 
      "x": 0.9037283, 
      "z": -0.025161969, 
      "visibility": 0.0, 
      "presence": 0.0
    }, 
    {
      "y": 0.76210535, 
      "x": 0.9161194, 
      "z": -0.032587074, 
      "visibility": 0.0, 
      "presence": 0.0
    }, 
    {
      "y": 0.7838151, 
      "x": 0.92598903, 
      "z": -0.03839245, 
      "visibility": 0.0, 
      "presence": 0.0
    }, 
    {
      "y": 0.8015176, 
      "x": 0.9352455, 
      "z": -0.04541663, 
      "visibility": 0.0, 
      "presence": 0.0
    }
  ]
}