{
  "landmark": [
    {
      "y": 0.6796133, 
      "x": 0.66658205, 
      "z": 1.7898901e-05, 
      "visibility": 0.0, 
      "presence": 0.0
    }, 
    {
      "y": 0.69484824, 
      "x": 0.64172554, 
      "z": -0.023254346, 
      "visibility": 0.0, 
      "presence": 0.0
    }, 
    {
      "y": 0.7201694, 
      "x": 0.6288302, 
      "z": -0.036022328, 
      "visibility": 0.0, 
      "presence": 0.0
    }, 
    {
      "y": 0.7455815, 
      "x": 0.6249051, 
      "z": -0.046690013, 
      "visibility": 0.0, 
      "presence": 0.0
    }, 
    {
      "y": 0.76692575, 
      "x": 0.6236117, 
      "z": -0.05699506, 
      "visibility": 0.0, 
      "presence": 0.0
    }, 
    {
      "y": 0.75897527, 
      "x": 0.65823317, 
      "z": -0.021546913, 
      "visibility": 0.0, 
      "presence": 0.0
    }, 
    {
      "y": 0.79949254, 
      "x": 0.6601401, 
      "z": -0.0326679, 
      "visibility": 0.0, 
      "presence": 0.0
    }, 
    {
      "y": 0.82363683, 
      "x": 0.6618299, 
      "z": -0.043698225, 
      "visibility": 0.0, 
      "presence": 0.0
    }, 
    {
      "y": 0.84228444, 
      "x": 0.66426164, 
      "z": -0.052522488, 
      "visibility": 0.0, 
      "presence": 0.0
    }, 
    {
      "y": 0.75879073, 
      "x": 0.6772009, 
      "z": -0.018993316, 
      "visibility": 0.0, 
      "presence": 0.0
    }, 
    {
      "y": 0.8053994, 
      "x": 0.6845583, 
      "z": -0.027621148, 
      "visibility": 0.0, 
      "presence": 0.0
    }, 
    {
      "y": 0.8332444, 
      "x": 0.6882852, 
      "z": -0.037503112, 
      "visibility": 0.0, 
      "presence": 0.0
    }, 
    {
      "y": 0.85677546, 
      "x": 0.69185054, 
      "z": -0.045904294, 
      "visibility": 0.0, 
      "presence": 0.0
    }, 
    {
      "y": 0.7509573, 
      "x": 0.6931397, 
      "z": -0.019008426, 
      "visibility": 0.0, 
      "presence": 0.0
    }, 
    {
      "y": 0.79260063, 
      "x": 0.7043214, 
      "z": -0.028225549, 
      "visibility": 0.0, 
      "presence": 0.0
    }, 
    {
      "y": 0.81778544, 
      "x": 0.7104503, 
      "z": -0.038832795, 
      "visibility": 0.0, 
      "presence": 0.0
    }, 
    {
      "y": 0.8392965, 
      "x": 0.71572727, 
      "z": -0.046448253, 
      "visibility": 0.0, 
      "presence": 0.0
    }, 
    {
      "y": 0.73753905, 
      "x": 0.7061654, 
      "z": -0.02076119, 
      "visibility": 0.0, 
      "presence": 0.0
    }, 
    {
      "y": 0.76648843, 
      "x": 0.7221165, 
      "z": -0.030220075, 
      "visibility": 0.0, 
      "presence": 0.0
    }, 
    {
      "y": 0.78449315, 
      "x": 0.73129123, 
      "z": -0.03680805, 
      "visibility": 0.0, 
      "presence": 0.0
    }, 
    {
      "y": 0.80245084, 
      "x": 0.7391056, 
      "z": -0.042580083, 
      "visibility": 0.0, 
      "presence": 0.0
    }
  ]
}