{
  "locationData": {
    "relativeBoundingBox": {
      "xmin": 0.79986006, 
      "width": 0.063581765, 
      "ymin": 0.6075573, 
      "height": 0.079477504
    }, 
    "relativeKeypoints": [
      {
        "y": 0.61706567, 
        "x": 0.8444628
      }, 
      {
        "y": 0.673818, 
        "x": 0.8143933
      }, 
      {
        "y": 0.6767872, 
        "x": 0.8339654
      }, 
      {
        "y": 0.67605776, 
        "x": 0.8507246
      }, 
      {
        "y": 0.67257464, 
        "x": 0.8647433
      }, 
      {
        "y": 0.6205063, 
        "x": 0.81776017
      }, 
      {
        "y": 0.646397, 
        "x": 0.7992354
      }
    ], 
    "format": "RELATIVE_BOUNDING_BOX"
  }, 
  "score": [
    0.99991107
  ], 
  "label": [
    "Palm"
  ]
}