{
  "locationData": {
    "relativeBoundingBox": {
      "xmin": 0.62245494, 
      "width": 0.06933588, 
      "ymin": 0.6923224, 
      "height": 0.08666992
    }, 
    "relativeKeypoints": [
      {
        "y": 0.6953424, 
        "x": 0.65953887
      }, 
      {
        "y": 0.77607435, 
        "x": 0.6567124
      }, 
      {
        "y": 0.7767683, 
        "x": 0.66083884
      }, 
      {
        "y": 0.7715389, 
        "x": 0.66313815
      }, 
      {
        "y": 0.7629663, 
        "x": 0.6643148
      }, 
      {
        "y": 0.7026595, 
        "x": 0.6521807
      }, 
      {
        "y": 0.73818743, 
        "x": 0.64743906
      }
    ], 
    "format": "RELATIVE_BOUNDING_BOX"
  }, 
  "score": [
    0.99928474
  ], 
  "label": [
    "Palm"
  ]
}